awkjeven_festivalookup_mcp/__init__.py
awkjeven_festivalookup_mcp-0.1.0.dist-info/WHEEL
awkjeven_festivalookup_mcp-0.1.0.dist-info/entry_points.txt
awkjeven_festivalookup_mcp-0.1.0.dist-info/METADATA
awkjeven_festivalookup_mcp-0.1.0.dist-info/RECORD
